iaed/__init__.py
iaed/avl.py
iaed/btree.py
iaed/fib.py
iaed/graph.py
iaed/hashdbl.py
iaed/hashext.py
iaed/hashlin.py
iaed/search.py
iaed/sorting.py
iaed-1.0.4.dist-info/licenses/LICENSE
iaed-1.0.4.dist-info/METADATA
iaed-1.0.4.dist-info/WHEEL
iaed-1.0.4.dist-info/top_level.txt
iaed-1.0.4.dist-info/RECORD
